[
        {
            "id": "secondary",
            "name": "Среднее"
        },
        {
            "id": "special_secondary",
            "name": "Среднее специальное"
        },
        {
            "id": "unfinished_higher",
            "name": "Неоконченное высшее"
        },
        {
            "id": "higher",
            "name": "Высшее"
        },
        {
            "id": "bachelor",
            "name": "Бакалавр"
        },
        {
            "id": "master",
            "name": "Магистр"
        },
        {
            "id": "candidate",
            "name": "Кандидат наук"
        },
        {
            "id": "doctor",
            "name": "Доктор наук"
        }
    ]
